LICENSE
README.md
setup.cfg
setup.py
sentry_dingtalk/__init__.py
sentry_dingtalk/plugin.py
sentry_dingtalk_source.egg-info/PKG-INFO
sentry_dingtalk_source.egg-info/SOURCES.txt
sentry_dingtalk_source.egg-info/dependency_links.txt
sentry_dingtalk_source.egg-info/entry_points.txt
sentry_dingtalk_source.egg-info/requires.txt
sentry_dingtalk_source.egg-info/top_level.txt