Metadata-Version: 2.1
Name: sentry-dingtalk-source
Version: 4.0.0
Summary: A sentry extension integrates DingTalk robot webhook forked from Jedore/sentry-dingtalk
Home-page: https://gitlab.xiaoman.cc/sourceliu/sentry-dingtalk-source
Author: source
Author-email: hao.zhu@shanbay.com
License: MIT
Keywords: sentry dingtalk
Platform: UNKNOWN
Classifier: License :: OSI Approved :: MIT License
Classifier: Programming Language :: Python
Classifier: Programming Language :: Python :: 3
Classifier: Programming Language :: Python :: 3.6
Classifier: Programming Language :: Python :: 3.7
Classifier: Programming Language :: Python :: Implementation :: CPython
Requires-Python: >=3.6.13
License-File: LICENSE
